netbox_reorder/__init__.py
netbox_reorder/ordering.py
netbox_reorder/migrations/0001_interface_reordering.py
netbox_reorder/migrations/__init__.py
netbox_reorder-1.0.1.dist-info/LICENSE.txt
netbox_reorder-1.0.1.dist-info/METADATA
netbox_reorder-1.0.1.dist-info/WHEEL
netbox_reorder-1.0.1.dist-info/top_level.txt
netbox_reorder-1.0.1.dist-info/RECORD
