Metadata-Version: 2.1
Name: netbox-reorder
Version: 1.0.1
Summary: NetBox Plugin to order interfaces more intuitively
Home-page: https://github.com/sjm-steffann/netbox-reorder
Author: Sander Steffann
Author-email: sander@isp.solcon.nl
License: Apache 2.0
Platform: UNKNOWN
Classifier: Development Status :: 3 - Alpha
Classifier: Framework :: Django
Classifier: Framework :: Django :: 3.0
Classifier: License :: OSI Approved :: Apache Software License
Classifier: Programming Language :: Python :: 3
Classifier: Programming Language :: Python :: 3.6
Classifier: Programming Language :: Python :: 3.7
Classifier: Programming Language :: Python :: 3.8
Requires-Python: >=3.6
Requires-Dist: setuptools
